[
    {
        "request_time": "2025-04-29 17:48:18.294171"
    },
    {
        "request_time": "2025-04-29 17:48:23.615317"
    },
    {
        "request_time": "2025-04-29 17:48:49.661970"
    },
    {
        "request_time": "2025-04-29 17:48:49.789871"
    },
    {
        "request_time": "2025-04-29 17:49:01.547716"
    },
    {
        "request_time": "2025-04-29 17:49:04.176277"
    },
    {
        "request_time": "2025-04-29 17:49:06.576935"
    },
    {
        "request_time": "2025-04-29 17:49:11.343723"
    },
    {
        "request_time": "2025-04-29 17:49:15.876628"
    },
    {
        "request_time": "2025-04-29 17:49:42.456862"
    },
    {
        "request_time": "2025-04-29 17:49:42.585016"
    },
    {
        "request_time": "2025-04-29 17:49:54.709181"
    },
    {
        "request_time": "2025-04-29 17:49:57.791512"
    },
    {
        "request_time": "2025-04-29 17:50:00.802390"
    },
    {
        "request_time": "2025-04-29 17:50:03.314926"
    },
    {
        "request_time": "2025-04-29 17:50:09.327902"
    },
    {
        "request_time": "2025-04-29 17:50:37.143530"
    },
    {
        "request_time": "2025-04-29 17:50:37.268678"
    },
    {
        "request_time": "2025-04-29 17:50:50.383998"
    },
    {
        "request_time": "2025-04-29 17:50:53.061046"
    },
    {
        "request_time": "2025-04-29 17:50:55.849048"
    },
    {
        "request_time": "2025-04-29 17:50:59.319992"
    },
    {
        "request_time": "2025-04-29 17:51:04.541277"
    },
    {
        "request_time": "2025-04-29 17:51:32.349007"
    },
    {
        "request_time": "2025-04-29 17:51:32.500628"
    },
    {
        "request_time": "2025-04-29 17:51:45.762892"
    },
    {
        "request_time": "2025-04-29 17:51:48.037980"
    },
    {
        "request_time": "2025-04-29 17:51:49.961166"
    },
    {
        "request_time": "2025-04-29 17:51:52.971715"
    },
    {
        "request_time": "2025-04-29 17:51:58.215537"
    },
    {
        "request_time": "2025-04-29 17:52:26.820805"
    },
    {
        "request_time": "2025-04-29 17:52:26.922592"
    },
    {
        "request_time": "2025-04-29 17:52:40.095197"
    },
    {
        "request_time": "2025-04-29 17:52:42.410836"
    },
    {
        "request_time": "2025-04-29 17:52:44.455397"
    },
    {
        "request_time": "2025-04-29 17:52:46.942377"
    },
    {
        "request_time": "2025-04-29 17:52:50.607155"
    },
    {
        "request_time": "2025-04-29 17:53:23.853913"
    },
    {
        "request_time": "2025-04-29 17:53:23.970005"
    },
    {
        "request_time": "2025-04-29 17:53:37.500304"
    },
    {
        "request_time": "2025-04-29 17:53:40.281846"
    },
    {
        "request_time": "2025-04-29 17:53:42.976571"
    },
    {
        "request_time": "2025-04-29 17:53:45.476504"
    },
    {
        "request_time": "2025-04-29 17:53:51.449696"
    },
    {
        "request_time": "2025-04-29 17:54:18.736022"
    },
    {
        "request_time": "2025-04-29 17:54:18.867883"
    },
    {
        "request_time": "2025-04-29 17:54:29.950582"
    },
    {
        "request_time": "2025-04-29 17:54:32.657459"
    },
    {
        "request_time": "2025-04-29 17:54:35.309247"
    },
    {
        "request_time": "2025-04-29 17:54:37.793002"
    },
    {
        "request_time": "2025-04-29 17:54:43.519879"
    },
    {
        "request_time": "2025-04-29 17:55:12.045406"
    },
    {
        "request_time": "2025-04-29 17:55:20.003188"
    },
    {
        "request_time": "2025-04-29 17:55:22.054943"
    },
    {
        "request_time": "2025-04-29 17:55:24.089228"
    },
    {
        "request_time": "2025-04-29 17:55:26.503294"
    },
    {
        "request_time": "2025-04-29 17:55:31.590449"
    },
    {
        "request_time": "2025-04-29 17:55:57.069908"
    },
    {
        "request_time": "2025-04-29 17:55:57.192795"
    },
    {
        "request_time": "2025-04-29 17:56:03.392707"
    },
    {
        "request_time": "2025-04-29 17:56:09.679508"
    },
    {
        "request_time": "2025-04-29 17:56:12.261662"
    },
    {
        "request_time": "2025-04-29 17:56:15.251231"
    },
    {
        "request_time": "2025-04-29 17:56:20.756502"
    },
    {
        "request_time": "2025-04-29 17:56:48.167290"
    },
    {
        "request_time": "2025-04-29 17:56:48.276273"
    },
    {
        "request_time": "2025-04-29 17:57:00.790549"
    },
    {
        "request_time": "2025-04-29 17:57:03.555509"
    },
    {
        "request_time": "2025-04-29 17:57:06.186050"
    },
    {
        "request_time": "2025-04-29 17:57:09.906336"
    },
    {
        "request_time": "2025-04-29 17:57:15.449760"
    },
    {
        "request_time": "2025-04-29 17:57:44.400026"
    },
    {
        "request_time": "2025-04-29 17:57:44.515144"
    },
    {
        "request_time": "2025-04-29 17:57:58.695025"
    },
    {
        "request_time": "2025-04-29 17:58:02.022044"
    },
    {
        "request_time": "2025-04-29 17:58:04.374943"
    },
    {
        "request_time": "2025-04-29 17:58:08.799550"
    },
    {
        "request_time": "2025-04-29 17:58:12.766678"
    },
    {
        "request_time": "2025-04-29 17:58:40.605847"
    },
    {
        "request_time": "2025-04-29 17:58:40.716019"
    },
    {
        "request_time": "2025-04-29 17:58:52.713336"
    },
    {
        "request_time": "2025-04-29 17:58:55.322693"
    },
    {
        "request_time": "2025-04-29 17:58:57.604945"
    },
    {
        "request_time": "2025-04-29 17:59:01.670663"
    },
    {
        "request_time": "2025-04-29 17:59:06.471586"
    },
    {
        "request_time": "2025-04-29 17:59:34.398723"
    },
    {
        "request_time": "2025-04-29 17:59:34.497846"
    },
    {
        "request_time": "2025-04-29 17:59:46.745288"
    },
    {
        "request_time": "2025-04-29 17:59:49.398282"
    },
    {
        "request_time": "2025-04-29 17:59:51.693395"
    },
    {
        "request_time": "2025-04-29 17:59:55.994842"
    },
    {
        "request_time": "2025-04-29 18:00:01.635142"
    },
    {
        "request_time": "2025-04-29 18:00:28.205292"
    },
    {
        "request_time": "2025-04-29 18:00:28.319927"
    },
    {
        "request_time": "2025-04-29 18:00:38.875282"
    },
    {
        "request_time": "2025-04-29 18:00:41.803608"
    },
    {
        "request_time": "2025-04-29 18:00:44.376893"
    },
    {
        "request_time": "2025-04-29 18:00:47.286688"
    },
    {
        "request_time": "2025-04-29 18:00:50.767559"
    },
    {
        "request_time": "2025-04-29 18:01:21.901901"
    },
    {
        "request_time": "2025-04-29 18:01:22.051135"
    },
    {
        "request_time": "2025-04-29 18:01:32.626218"
    },
    {
        "request_time": "2025-04-29 18:01:34.627732"
    },
    {
        "request_time": "2025-04-29 18:01:36.526205"
    },
    {
        "request_time": "2025-04-29 18:01:39.360055"
    },
    {
        "request_time": "2025-04-29 18:01:43.378923"
    },
    {
        "request_time": "2025-04-29 18:02:13.679970"
    },
    {
        "request_time": "2025-04-29 18:02:13.784464"
    },
    {
        "request_time": "2025-04-29 18:02:22.617246"
    },
    {
        "request_time": "2025-04-29 18:02:25.255115"
    },
    {
        "request_time": "2025-04-29 18:02:27.814999"
    },
    {
        "request_time": "2025-04-29 18:02:30.289215"
    },
    {
        "request_time": "2025-04-29 18:02:32.813886"
    },
    {
        "request_time": "2025-04-29 18:03:07.094603"
    },
    {
        "request_time": "2025-04-29 18:03:07.200042"
    },
    {
        "request_time": "2025-04-29 18:03:14.667677"
    },
    {
        "request_time": "2025-04-29 18:03:16.571232"
    },
    {
        "request_time": "2025-04-29 18:03:18.472882"
    },
    {
        "request_time": "2025-04-29 18:03:20.940402"
    },
    {
        "request_time": "2025-04-29 18:03:23.528592"
    },
    {
        "request_time": "2025-04-29 18:03:59.684336"
    },
    {
        "request_time": "2025-04-29 18:03:59.797524"
    },
    {
        "request_time": "2025-04-29 18:04:08.510976"
    },
    {
        "request_time": "2025-04-29 18:04:11.173945"
    },
    {
        "request_time": "2025-04-29 18:04:13.750212"
    },
    {
        "request_time": "2025-04-29 18:04:16.268276"
    },
    {
        "request_time": "2025-04-29 18:04:18.896060"
    },
    {
        "request_time": "2025-04-29 18:04:52.837856"
    },
    {
        "request_time": "2025-04-29 18:04:52.959168"
    },
    {
        "request_time": "2025-04-29 18:05:02.114354"
    },
    {
        "request_time": "2025-04-29 18:05:04.723572"
    },
    {
        "request_time": "2025-04-29 18:05:06.619368"
    },
    {
        "request_time": "2025-04-29 18:05:10.829734"
    },
    {
        "request_time": "2025-04-29 18:05:14.177888"
    },
    {
        "request_time": "2025-04-29 18:05:44.390834"
    },
    {
        "request_time": "2025-04-29 18:05:52.097682"
    },
    {
        "request_time": "2025-04-29 18:05:54.353360"
    },
    {
        "request_time": "2025-04-29 18:05:56.230484"
    },
    {
        "request_time": "2025-04-29 18:05:59.479594"
    },
    {
        "request_time": "2025-04-29 18:06:04.047814"
    },
    {
        "request_time": "2025-04-29 18:06:31.470633"
    },
    {
        "request_time": "2025-04-29 18:06:31.571411"
    },
    {
        "request_time": "2025-04-29 18:06:39.561975"
    },
    {
        "request_time": "2025-04-29 18:06:41.775462"
    },
    {
        "request_time": "2025-04-29 18:06:43.941350"
    },
    {
        "request_time": "2025-04-29 18:06:46.381372"
    },
    {
        "request_time": "2025-04-29 18:06:50.377937"
    },
    {
        "request_time": "2025-04-29 18:07:16.701388"
    },
    {
        "request_time": "2025-04-29 18:07:16.802985"
    },
    {
        "request_time": "2025-04-29 18:07:27.056595"
    },
    {
        "request_time": "2025-04-29 18:07:29.770890"
    },
    {
        "request_time": "2025-04-29 18:07:32.079246"
    },
    {
        "request_time": "2025-04-29 18:07:37.163556"
    },
    {
        "request_time": "2025-04-29 18:07:42.386097"
    },
    {
        "request_time": "2025-04-29 18:08:09.424477"
    },
    {
        "request_time": "2025-04-29 18:08:09.534867"
    },
    {
        "request_time": "2025-04-29 18:08:21.364937"
    },
    {
        "request_time": "2025-04-29 18:08:23.929759"
    },
    {
        "request_time": "2025-04-29 18:08:26.335052"
    },
    {
        "request_time": "2025-04-29 18:08:32.301588"
    },
    {
        "request_time": "2025-04-29 18:08:37.167861"
    },
    {
        "request_time": "2025-04-29 18:09:02.162688"
    },
    {
        "request_time": "2025-04-29 18:09:02.303046"
    },
    {
        "request_time": "2025-04-29 18:09:13.090522"
    },
    {
        "request_time": "2025-04-29 18:09:16.565207"
    },
    {
        "request_time": "2025-04-29 18:09:19.016084"
    },
    {
        "request_time": "2025-04-29 18:09:28.081815"
    },
    {
        "request_time": "2025-04-29 18:09:33.736284"
    },
    {
        "request_time": "2025-04-29 18:09:59.340033"
    },
    {
        "request_time": "2025-04-29 18:09:59.456546"
    },
    {
        "request_time": "2025-04-29 18:10:10.049461"
    },
    {
        "request_time": "2025-04-29 18:10:12.697451"
    },
    {
        "request_time": "2025-04-29 18:10:15.217332"
    },
    {
        "request_time": "2025-04-29 18:10:19.880829"
    },
    {
        "request_time": "2025-04-29 18:10:27.273509"
    },
    {
        "request_time": "2025-04-29 18:10:52.381828"
    },
    {
        "request_time": "2025-04-29 18:10:52.482615"
    },
    {
        "request_time": "2025-04-29 18:11:05.095156"
    },
    {
        "request_time": "2025-04-29 18:11:07.345564"
    },
    {
        "request_time": "2025-04-29 18:11:09.795598"
    },
    {
        "request_time": "2025-04-29 18:11:13.979748"
    },
    {
        "request_time": "2025-04-29 18:11:21.778980"
    },
    {
        "request_time": "2025-04-29 18:11:46.369642"
    },
    {
        "request_time": "2025-04-29 18:11:46.470201"
    },
    {
        "request_time": "2025-04-29 18:12:01.100524"
    },
    {
        "request_time": "2025-04-29 18:12:03.768799"
    },
    {
        "request_time": "2025-04-29 18:12:06.469771"
    },
    {
        "request_time": "2025-04-29 18:12:09.103764"
    },
    {
        "request_time": "2025-04-29 18:12:17.277750"
    },
    {
        "request_time": "2025-04-29 18:12:44.007192"
    },
    {
        "request_time": "2025-04-29 18:12:44.111198"
    },
    {
        "request_time": "2025-04-29 18:13:00.150162"
    },
    {
        "request_time": "2025-04-29 18:13:03.221584"
    },
    {
        "request_time": "2025-04-29 18:13:05.445595"
    },
    {
        "request_time": "2025-04-29 18:13:08.568046"
    },
    {
        "request_time": "2025-04-29 18:13:15.202922"
    },
    {
        "request_time": "2025-04-29 18:13:40.693353"
    },
    {
        "request_time": "2025-04-29 18:13:40.840251"
    },
    {
        "request_time": "2025-04-29 18:13:53.150529"
    },
    {
        "request_time": "2025-04-29 18:13:55.624539"
    },
    {
        "request_time": "2025-04-29 18:13:58.606249"
    },
    {
        "request_time": "2025-04-29 18:14:03.168475"
    },
    {
        "request_time": "2025-04-29 18:14:06.835585"
    },
    {
        "request_time": "2025-04-29 18:14:31.802859"
    },
    {
        "request_time": "2025-04-29 18:14:31.938106"
    },
    {
        "request_time": "2025-04-29 18:14:40.543343"
    },
    {
        "request_time": "2025-04-29 18:14:49.753715"
    },
    {
        "request_time": "2025-04-29 18:14:52.109533"
    },
    {
        "request_time": "2025-04-29 18:14:54.626175"
    },
    {
        "request_time": "2025-04-29 18:14:58.239783"
    },
    {
        "request_time": "2025-04-29 18:15:22.701610"
    },
    {
        "request_time": "2025-04-29 18:15:54.244026"
    },
    {
        "request_time": "2025-04-29 18:15:55.920041"
    },
    {
        "request_time": "2025-04-29 18:15:57.605378"
    },
    {
        "request_time": "2025-04-29 18:16:01.934842"
    },
    {
        "request_time": "2025-04-29 18:16:03.357383"
    },
    {
        "request_time": "2025-04-29 18:16:29.158225"
    },
    {
        "request_time": "2025-04-29 18:16:29.228585"
    },
    {
        "request_time": "2025-04-29 18:16:34.396010"
    },
    {
        "request_time": "2025-04-29 18:16:36.716371"
    },
    {
        "request_time": "2025-04-29 18:16:38.267199"
    },
    {
        "request_time": "2025-04-29 18:16:42.694067"
    },
    {
        "request_time": "2025-04-29 18:16:46.831255"
    },
    {
        "request_time": "2025-04-29 18:17:12.303156"
    },
    {
        "request_time": "2025-04-29 18:17:12.452031"
    },
    {
        "request_time": "2025-04-29 18:17:21.635547"
    },
    {
        "request_time": "2025-04-29 18:17:23.853330"
    },
    {
        "request_time": "2025-04-29 18:17:25.664777"
    },
    {
        "request_time": "2025-04-29 18:17:28.073041"
    },
    {
        "request_time": "2025-04-29 18:17:31.699696"
    },
    {
        "request_time": "2025-04-29 18:18:01.702412"
    },
    {
        "request_time": "2025-04-29 18:18:01.802150"
    },
    {
        "request_time": "2025-04-29 18:18:14.062482"
    },
    {
        "request_time": "2025-04-29 18:18:16.593517"
    },
    {
        "request_time": "2025-04-29 18:18:19.063205"
    },
    {
        "request_time": "2025-04-29 18:18:21.563319"
    },
    {
        "request_time": "2025-04-29 18:18:26.966355"
    },
    {
        "request_time": "2025-04-29 18:18:56.467343"
    },
    {
        "request_time": "2025-04-29 18:18:56.575021"
    },
    {
        "request_time": "2025-04-29 18:19:08.571355"
    },
    {
        "request_time": "2025-04-29 18:19:10.545846"
    },
    {
        "request_time": "2025-04-29 18:19:12.542185"
    },
    {
        "request_time": "2025-04-29 18:19:14.992830"
    },
    {
        "request_time": "2025-04-29 18:19:20.444731"
    },
    {
        "request_time": "2025-04-29 18:19:50.282899"
    },
    {
        "request_time": "2025-04-29 18:19:50.394020"
    },
    {
        "request_time": "2025-04-29 18:20:02.102810"
    },
    {
        "request_time": "2025-04-29 18:20:04.497251"
    },
    {
        "request_time": "2025-04-29 18:20:06.841931"
    },
    {
        "request_time": "2025-04-29 18:20:09.322640"
    },
    {
        "request_time": "2025-04-29 18:20:14.988090"
    },
    {
        "request_time": "2025-04-29 18:20:44.593802"
    },
    {
        "request_time": "2025-04-29 18:20:44.706008"
    },
    {
        "request_time": "2025-04-29 18:20:55.761105"
    },
    {
        "request_time": "2025-04-29 18:20:57.973480"
    },
    {
        "request_time": "2025-04-29 18:21:00.070266"
    },
    {
        "request_time": "2025-04-29 18:21:04.453967"
    },
    {
        "request_time": "2025-04-29 18:21:09.013932"
    },
    {
        "request_time": "2025-04-29 18:21:36.021120"
    },
    {
        "request_time": "2025-04-29 18:22:10.579090"
    },
    {
        "request_time": "2025-04-29 18:22:12.146372"
    },
    {
        "request_time": "2025-04-29 18:22:14.698224"
    },
    {
        "request_time": "2025-04-29 18:22:19.070231"
    },
    {
        "request_time": "2025-04-29 18:22:24.425342"
    },
    {
        "request_time": "2025-04-29 18:22:52.323730"
    },
    {
        "request_time": "2025-04-29 18:22:52.396163"
    },
    {
        "request_time": "2025-04-29 18:23:03.935601"
    },
    {
        "request_time": "2025-04-29 18:23:06.337693"
    },
    {
        "request_time": "2025-04-29 18:23:08.714722"
    },
    {
        "request_time": "2025-04-29 18:23:11.095569"
    },
    {
        "request_time": "2025-04-29 18:23:16.473042"
    },
    {
        "request_time": "2025-04-29 18:23:47.137765"
    },
    {
        "request_time": "2025-04-29 18:23:47.296460"
    },
    {
        "request_time": "2025-04-29 18:23:59.176926"
    },
    {
        "request_time": "2025-04-29 18:24:02.340971"
    },
    {
        "request_time": "2025-04-29 18:24:05.457021"
    },
    {
        "request_time": "2025-04-29 18:24:07.860090"
    },
    {
        "request_time": "2025-04-29 18:24:13.568907"
    },
    {
        "request_time": "2025-04-29 18:24:39.498181"
    },
    {
        "request_time": "2025-04-29 18:24:39.654354"
    },
    {
        "request_time": "2025-04-29 18:24:50.186115"
    },
    {
        "request_time": "2025-04-29 18:24:53.142589"
    },
    {
        "request_time": "2025-04-29 18:24:55.585043"
    },
    {
        "request_time": "2025-04-29 18:24:57.523722"
    },
    {
        "request_time": "2025-04-29 18:24:59.519363"
    },
    {
        "request_time": "2025-04-29 18:25:31.552111"
    },
    {
        "request_time": "2025-04-29 18:25:31.652184"
    },
    {
        "request_time": "2025-04-29 18:25:39.133536"
    },
    {
        "request_time": "2025-04-29 18:25:43.340683"
    },
    {
        "request_time": "2025-04-29 18:25:45.661428"
    },
    {
        "request_time": "2025-04-29 18:25:47.501780"
    },
    {
        "request_time": "2025-04-29 18:25:49.512724"
    },
    {
        "request_time": "2025-04-29 18:26:20.234139"
    },
    {
        "request_time": "2025-04-29 18:26:20.360611"
    },
    {
        "request_time": "2025-04-29 18:26:27.223260"
    },
    {
        "request_time": "2025-04-29 18:26:29.523021"
    },
    {
        "request_time": "2025-04-29 18:26:31.421591"
    },
    {
        "request_time": "2025-04-29 18:26:34.564272"
    },
    {
        "request_time": "2025-04-29 18:26:36.474484"
    },
    {
        "request_time": "2025-04-29 18:27:15.346856"
    },
    {
        "request_time": "2025-04-29 18:27:15.452573"
    },
    {
        "request_time": "2025-04-29 18:27:21.605579"
    },
    {
        "request_time": "2025-04-29 18:27:23.635899"
    },
    {
        "request_time": "2025-04-29 18:27:25.650870"
    },
    {
        "request_time": "2025-04-29 18:27:27.590031"
    },
    {
        "request_time": "2025-04-29 18:27:29.039933"
    },
    {
        "request_time": "2025-04-29 18:27:54.332553"
    },
    {
        "request_time": "2025-04-29 18:27:54.437839"
    },
    {
        "request_time": "2025-04-29 18:28:00.772476"
    },
    {
        "request_time": "2025-04-29 18:28:02.633748"
    },
    {
        "request_time": "2025-04-29 18:28:04.483971"
    },
    {
        "request_time": "2025-04-29 18:28:09.781989"
    },
    {
        "request_time": "2025-04-29 18:28:12.867701"
    }
]